comtrade.py
comtrade-0.1.2.dist-info/LICENSE.md
comtrade-0.1.2.dist-info/METADATA
comtrade-0.1.2.dist-info/WHEEL
comtrade-0.1.2.dist-info/top_level.txt
comtrade-0.1.2.dist-info/RECORD
