Metadata-Version: 2.1
Name: comtrade
Version: 0.1.2
Summary: A module designed to read Common Format for Transient Data Exchange (COMTRADE) file format.
Home-page: https://github.com/dparrini/python-comtrade
Author: David Parrini
Author-email: d.parrini@gmail.com
Classifier: Programming Language :: Python :: 3
Classifier: License :: OSI Approved :: MIT License
Classifier: Operating System :: OS Independent
Requires-Python: >=3.6
License-File: LICENSE.md
